{
  "heroes": [
    {
      "id": 1,
      "name": "Первый герой",
      "description": "Первый герой в рейтинге!",
      "element": "fire"
    },
    {
      "id": 2,
      "name": "Неизвестный герой",
      "description": "Скрывающийся в тени",
      "element": "wind"
    },
    {
      "id": "df5b291d-a82a-4071-865a-b184be3f4187",
      "name": "dsad",
      "description": "dsad",
      "element": "fire"
    },
    {
      "id": "455f4f53-c5af-4cdc-b018-f0ae96875453",
      "name": "dsafdf",
      "description": "fdfsdf",
      "element": "water"
    },
    {
      "id": "a5d6dee3-5112-4d45-929b-1bc9698bbe8c",
      "name": "dasdas",
      "description": "dsadas",
      "element": "fire"
    }
  ],
  "filters": [
    {
      "name": "all",
      "label": "Все",
      "className": "btn-outline-dark"
    },
    {
      "name": "fire",
      "label": "Огонь",
      "className": "btn-danger"
    },
    {
      "name": "water",
      "label": "Вода",
      "className": "btn-primary"
    },
    {
      "name": "wind",
      "label": "Ветер",
      "className": "btn-success"
    },
    {
      "name": "earth",
      "label": "Земля",
      "className": "btn-secondary"
    }
  ]
}